MANIFEST.in
README.md
requirements.txt
setup.cfg
setup.py
redmsg_logger/__init__.py
redmsg_logger/logger.py
redmsg_logger.egg-info/PKG-INFO
redmsg_logger.egg-info/SOURCES.txt
redmsg_logger.egg-info/dependency_links.txt
redmsg_logger.egg-info/entry_points.txt
redmsg_logger.egg-info/requires.txt
redmsg_logger.egg-info/top_level.txt
redmsg_logger/handlers/__init__.py
redmsg_logger/handlers/base.py
redmsg_logger/handlers/exc.py
redmsg_logger/handlers/sqlalchemy.py