Metadata-Version: 1.1
Name: redmsg-logger
Version: 0.2.1
Summary: Service to log RedMsg messages to various backends
Home-page: https://github.com/ivotkv/redmsg-logger
Author: Ivo Tzvetkov
Author-email: ivotkv@gmail.com
License: MIT
Download-URL: https://github.com/ivotkv/redmsg-logger/tarball/v0.2.1
Keywords: redis,messaging,playback,redmsg,logger
Platform: UNKNOWN
Classifier: Development Status :: 5 - Production/Stable
Classifier: Intended Audience :: Developers
Classifier: License :: OSI Approved :: MIT License
Classifier: Operating System :: OS Independent
Classifier: Programming Language :: Python :: 2.7
Classifier: Programming Language :: Python :: 3.3
Classifier: Programming Language :: Python :: 3.4
Classifier: Programming Language :: Python :: 3.5
Classifier: Programming Language :: Python :: 3.6
Classifier: Topic :: Software Development
